<?xml version="1.0" encoding="UTF-8"?>
<con:soapui-project id="519ed4c3-e571-4cd0-af85-6c373cf9ebaa" created="3.46.0" activeEnvironment="Default environment" encryptionMode="Not encrypted" name="REST Project 2" projectVersion="" updated="3.46.0 2023-05-11T09:29:01Z" xmlns:con="http://eviware.com/soapui/config">
  <con:settings/>
  <con:interface xsi:type="con:RestService" id="18fa0e81-b4a8-479d-b526-9759c601ecd9" wadlVersion="http://wadl.dev.java.net/2009/02" name="https://api.github.com" type="rest" xmlns:xsi="http://www.w3.org/2001/XMLSchema-instance">
    <con:settings id="14f611f5-f1a5-46b7-8d7e-383245909ea2"/>
    <con:definitionCache type="TEXT" rootPart=""/>
    <con:endpoints>
      <con:endpoint>https://api.github.com</con:endpoint>
    </con:endpoints>
    <con:resource name="Emails" path="/user/emails" id="ba48a636-5a93-4f48-9c21-11d5bfb3b64a">
      <con:settings/>
      <con:parameters/>
      <con:method name="Emails" id="eac25f6e-24d1-4d20-afb6-4b2695395484" method="GET">
        <con:settings/>
        <con:parameters/>
        <con:representation type="RESPONSE">
          <con:mediaType>application/json; charset=utf-8</con:mediaType>
          <con:status>200</con:status>
          <con:params/>
          <con:element>Response</con:element>
        </con:representation>
        <con:request name="Request 1" id="9631a6ee-c9c0-4220-99dc-e21031cfeeff" mediaType="application/json">
          <con:settings/>
          <con:endpoint>https://api.github.com</con:endpoint>
          <con:parameters/>
        </con:request>
      </con:method>
    </con:resource>
    <con:resource name="Keys" path="/user/keys" id="cb195ea1-8a82-45f4-bda3-2a9db17012e4">
      <con:settings/>
      <con:parameters/>
      <con:method name="Keys" id="2d1aee15-4937-45dd-98af-a90485e2b8ac" method="POST">
        <con:settings/>
        <con:parameters/>
        <con:representation type="RESPONSE">
          <con:mediaType>application/json; charset=utf-8</con:mediaType>
          <con:status>201</con:status>
          <con:params/>
          <con:element xmlns:keys="https://api.github.com/user/keys">keys:Response</con:element>
        </con:representation>
        <con:representation type="REQUEST">
          <con:mediaType>application/json</con:mediaType>
          <con:params/>
        </con:representation>
        <con:request name="Request 1" id="aa82bf0a-4131-41b0-bcfb-42dd1d5d8e9d" mediaType="application/json">
          <con:settings/>
          <con:endpoint>https://api.github.com</con:endpoint>
          <con:parameters/>
        </con:request>
      </con:method>
    </con:resource>
    <con:resource name="KeyId" path="/user/keys/{keyId}" id="dd5c71f3-6ac2-4023-9417-496e7c8a7c4f">
      <con:settings/>
      <con:parameters/>
      <con:method name="KeyId" id="7f77e32a-7c6d-4ad5-9976-432544f6ac88" method="DELETE">
        <con:settings/>
        <con:parameters>
          <con:parameter required="true">
            <con:name>keyId</con:name>
            <con:value>keyId</con:value>
            <con:style>TEMPLATE</con:style>
            <con:default>keyId</con:default>
            <con:path xsi:nil="true"/>
            <con:description xsi:nil="true"/>
          </con:parameter>
        </con:parameters>
        <con:representation type="REQUEST">
          <con:mediaType>application/json</con:mediaType>
          <con:params/>
        </con:representation>
        <con:representation type="RESPONSE">
          <con:mediaType xsi:nil="true"/>
          <con:status>204</con:status>
          <con:params/>
          <con:element>data</con:element>
        </con:representation>
        <con:request name="Request 1" id="16832151-c7b9-4b15-952c-b4b61bcb6682" mediaType="application/json">
          <con:settings/>
          <con:endpoint>https://api.github.com</con:endpoint>
          <con:parameters>
            <con:entry key="keyId" value="keyId"/>
          </con:parameters>
          <con:parameterOrder>
            <con:entry>keyId</con:entry>
          </con:parameterOrder>
        </con:request>
      </con:method>
    </con:resource>
  </con:interface>
  <con:testSuite id="540500ad-8612-497d-9e2d-d4132098d4eb" name="https://api.github.com Test Suite">
    <con:settings id="e85272da-23d3-4ef2-a442-f4f5bc61b96d"/>
    <con:runType>SEQUENTIAL</con:runType>
    <con:testCase id="d2552a67-5901-4934-8379-72cbcf3b4269" discardOkResults="false" failOnError="false" failTestCaseOnErrors="true" keepSession="false" name="Test Case" searchProperties="true" timeout="0">
      <con:settings/>
      <con:testStep type="restrequest" name="Request 1" id="2a5a47c0-9d54-477b-81b1-0ed35ca73691">
        <con:settings/>
        <con:config service="https://api.github.com" resourcePath="/user/emails" methodName="Emails" xsi:type="con:RestRequestStep" xmlns:xsi="http://www.w3.org/2001/XMLSchema-instance">
          <con:restRequest name="Request 1" id="9631a6ee-c9c0-4220-99dc-e21031cfeeff" mediaType="application/json">
            <con:settings>
              <con:setting id="com.eviware.soapui.impl.wsdl.WsdlRequest@request-headers">&lt;xml-fragment/></con:setting>
            </con:settings>
            <con:endpoint>https://api.github.com</con:endpoint>
            <con:request/>
            <con:originalUri>https://api.github.com/user/emails</con:originalUri>
            <con:assertion type="Valid HTTP Status Codes" id="a4974694-aebd-4ca8-a1e1-b9e453820d3c" name="Valid HTTP Status Codes">
              <con:settings/>
              <con:configuration>
                <codes>200</codes>
              </con:configuration>
            </con:assertion>
            <con:credentials>
              <con:selectedAuthProfile>admin_bakki_2</con:selectedAuthProfile>
              <con:authType>No Authorization</con:authType>
            </con:credentials>
            <con:jmsConfig JMSDeliveryMode="PERSISTENT"/>
            <con:parameters/>
          </con:restRequest>
        </con:config>
      </con:testStep>
      <con:testStep type="restrequest" name="Request 2" id="2db63f77-c436-4c64-9ffb-6963d56a956f">
        <con:settings/>
        <con:config service="https://api.github.com" resourcePath="/user/keys" methodName="Keys" xsi:type="con:RestRequestStep" xmlns:xsi="http://www.w3.org/2001/XMLSchema-instance">
          <con:restRequest name="Request 2" id="aa82bf0a-4131-41b0-bcfb-42dd1d5d8e9d" mediaType="application/json" postQueryString="false">
            <con:settings>
              <con:setting id="com.eviware.soapui.impl.wsdl.WsdlRequest@request-headers">&lt;xml-fragment/></con:setting>
            </con:settings>
            <con:endpoint>https://api.github.com</con:endpoint>
            <con:request>{
	"title": "TestKey",
	"key":"ssh-ed25519 AAAAC3NzaC1lZDI1NTE5AAAAIMXZpcqwP+m6IAQlsqu4+BvlF634W96OL2EtwE//zQjf"
	
}</con:request>
            <con:originalUri>https://api.github.com/user/keys</con:originalUri>
            <con:assertion type="Valid HTTP Status Codes" id="1825f5e5-42fd-491c-bd2a-143f946d7db4" name="Valid HTTP Status Codes">
              <con:settings/>
              <con:configuration>
                <codes>201</codes>
              </con:configuration>
            </con:assertion>
            <con:credentials>
              <con:selectedAuthProfile>admin_bakki_2</con:selectedAuthProfile>
              <con:authType>No Authorization</con:authType>
            </con:credentials>
            <con:jmsConfig JMSDeliveryMode="PERSISTENT"/>
            <con:parameters/>
          </con:restRequest>
        </con:config>
      </con:testStep>
      <con:testStep type="transfer" name="Property Transfer" id="dc289700-67a0-4097-879c-b62df5c397d1">
        <con:settings/>
        <con:config xsi:type="con:PropertyTransfersStep" xmlns:xsi="http://www.w3.org/2001/XMLSchema-instance">
          <con:transfers setNullOnMissingSource="true" transferTextContent="true" failOnError="true" ignoreEmpty="false" transferToAll="false" entitize="false" transferChildNodes="false">
            <con:name>keyId</con:name>
            <con:sourceType>Response</con:sourceType>
            <con:sourceStep>Request 2</con:sourceStep>
            <con:sourcePath>$['id']</con:sourcePath>
            <con:targetType>keyId</con:targetType>
            <con:targetStep>Request 3</con:targetStep>
            <con:targetPath/>
            <con:type>JSONPATH</con:type>
            <con:upgraded>true</con:upgraded>
          </con:transfers>
        </con:config>
      </con:testStep>
      <con:testStep type="restrequest" name="Request 3" id="cd48d3d4-b4a8-4446-bdc8-7f783dc1943a">
        <con:settings/>
        <con:config service="https://api.github.com" resourcePath="/user/keys/{keyId}" methodName="KeyId" xsi:type="con:RestRequestStep" xmlns:xsi="http://www.w3.org/2001/XMLSchema-instance">
          <con:restRequest name="Request 3" id="16832151-c7b9-4b15-952c-b4b61bcb6682" mediaType="application/json" postQueryString="false">
            <con:settings>
              <con:setting id="com.eviware.soapui.impl.wsdl.WsdlRequest@request-headers">&lt;xml-fragment/></con:setting>
            </con:settings>
            <con:endpoint>https://api.github.com</con:endpoint>
            <con:request/>
            <con:originalUri>https://api.github.com/user/keys/82616290</con:originalUri>
            <con:assertion type="Valid HTTP Status Codes" id="ead70147-f731-4f8c-ae59-0562c5e3db76" name="Valid HTTP Status Codes">
              <con:settings/>
              <con:configuration>
                <codes>204</codes>
              </con:configuration>
            </con:assertion>
            <con:credentials>
              <con:selectedAuthProfile>admin_bakki_2</con:selectedAuthProfile>
              <con:authType>No Authorization</con:authType>
            </con:credentials>
            <con:jmsConfig JMSDeliveryMode="PERSISTENT"/>
            <con:parameters>
              <con:entry key="keyId" value="82616290"/>
            </con:parameters>
            <con:parameterOrder>
              <con:entry>keyId</con:entry>
            </con:parameterOrder>
          </con:restRequest>
        </con:config>
      </con:testStep>
      <con:properties/>
      <con:reportParameters/>
    </con:testCase>
    <con:properties/>
    <con:reportParameters/>
  </con:testSuite>
  <con:properties/>
  <con:wssContainer/>
  <con:databaseConnectionContainer/>
  <con:jmsConnectionContainer/>
  <con:oAuth2ProfileContainer>
    <con:oAuth2Profile>
      <con:name>admin_bakki_2</con:name>
      <con:type>OAuth 2.0</con:type>
      <con:accessToken>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</con:accessToken>
      <con:accessTokenPosition>HEADER</con:accessTokenPosition>
      <con:accessTokenStatus>ENTERED_MANUALLY</con:accessTokenStatus>
      <con:accessTokenStartingStatus>ENTERED_MANUALLY</con:accessTokenStartingStatus>
      <con:oAuth2Flow>AUTHORIZATION_CODE_GRANT</con:oAuth2Flow>
      <con:refreshAccessTokenMethod>AUTOMATIC</con:refreshAccessTokenMethod>
      <con:jwtConfiguration/>
      <con:responseType>id_token</con:responseType>
    </con:oAuth2Profile>
  </con:oAuth2ProfileContainer>
  <con:oAuth1ProfileContainer/>
  <con:reporting>
    <con:xmlTemplates/>
    <con:parameters/>
  </con:reporting>
  <con:eventHandlers type="RequestFilter.filterRequest" name="RequestFilter.filterRequest">
    <con:script>// Sample event script to add custom HTTP header to all outgoing REST, SOAP and HTTP(S) calls
// This code is often used for adding custom authentication to ReadyAPI functional tests

// If hardcoding the token, uncomment and change line 5
// token = '4567'

// If your token is parameterized in Project level custom property, uncomment line 8
// token = request.parent.testCase.testSuite.project.getProperty('auth_token').getValue()

// To modify all outgoing calls, remove comments from lines 11 to 16
// headers = request.requestHeaders
// if (headers.containsKey('auth_token2') == false) {
//   headers.put('auth_token2', token)
//   request.requestHeaders = headers
// }</con:script>
  </con:eventHandlers>
  <con:eventHandlers type="TestRunListener.afterStep" name="TestRunListener.afterStep">
    <con:script>// Save all test step results into files
// Change the directory path in line 5 to a location where you want to store details
// then uncomment lines 5 to 10

// filePath = 'C:\\tempOutputDirectory\\'
// fos = new java.io.FileOutputStream(filePath + testStepResult.testStep.label + '.txt', true)
// pw = new java.io.PrintWriter(fos)
// testStepResult.writeTo(pw)
// pw.close()
// fos.close()</con:script>
  </con:eventHandlers>
  <con:authRepository>
    <con:oAuth20AuthEntry>
      <con:name>admin_bakki_2</con:name>
      <con:type>OAuth 2.0</con:type>
      <con:accessToken>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</con:accessToken>
      <con:accessTokenPosition>HEADER</con:accessTokenPosition>
      <con:accessTokenStatus>ENTERED_MANUALLY</con:accessTokenStatus>
      <con:accessTokenStartingStatus>ENTERED_MANUALLY</con:accessTokenStartingStatus>
      <con:oAuth2Flow>AUTHORIZATION_CODE_GRANT</con:oAuth2Flow>
      <con:refreshAccessTokenMethod>AUTOMATIC</con:refreshAccessTokenMethod>
      <con:jwtConfiguration/>
      <con:responseType>id_token</con:responseType>
    </con:oAuth20AuthEntry>
  </con:authRepository>
  <con:tags/>
</con:soapui-project>
